{"title": {"az": "Sağdan üçüncü", "en": "Third from right", "ru": "Третья справа"}, "statement": {"az": "Natural ədəd verilmişdir. Onun sağdan üçüncü rəqəmini verin.\r\n", "en": "Given positive integer. Print its third digit from the right.\r\n", "ru": "Дано натуральное число. Вывести его третью цифру справа."}, "input_format": {"az": "Yeganə natural **n** (**100** ≤ **n** ≤ $10^9$) ədədi.\r\n", "en": "One positive integer **n** (**100** ≤ **n** ≤ $10^9$).\r\n", "ru": "Одно натуральное число **n** (**100** ≤ **n** ≤ $10^9$).\r\n"}, "output_format": {"az": "**n** ədədinin sağdan üçüncü rəqəmini verin.", "en": "Print the third digit of number **n** from the right.", "ru": "Вывести третью цифру справа в числе **n**."}, "notes": {"az": "", "en": "", "ru": ""}, "scores_format": {"az": "", "en": "", "ru": ""}, "source": {"az": "", "en": "", "ru": ""}, "author": {"az": "", "en": "", "ru": ""}}